Unicorn_lib/__init__.py
Unicorn_lib/banagher_links.py
unicorn_lib-0.2.3.dist-info/METADATA
unicorn_lib-0.2.3.dist-info/WHEEL
unicorn_lib-0.2.3.dist-info/top_level.txt
unicorn_lib-0.2.3.dist-info/RECORD
