Metadata-Version: 2.4
Name: Unicorn_lib
Version: 0.2.3
Summary: リアルタイムで”ユニコーンプログラミング”ができます。
Author: Gingyer
Classifier: Programming Language :: Python :: 3
Classifier: License :: OSI Approved :: MIT License
Classifier: Operating System :: OS Independent
Requires-Python: >=3.6
Dynamic: author
Dynamic: classifier
Dynamic: description-content-type
Dynamic: requires-python
Dynamic: summary
